pgtree/__init__.py
pgtree/pgtree
pgtree/pgtree.py
pgtree/version.py
pgtree-1.1.9.data/scripts/pgtree
pgtree-1.1.9.dist-info/licenses/LICENSE
pgtree-1.1.9.dist-info/METADATA
pgtree-1.1.9.dist-info/WHEEL
pgtree-1.1.9.dist-info/top_level.txt
pgtree-1.1.9.dist-info/RECORD
