Metadata-Version: 2.4
Name: pgtree
Version: 1.1.9
Summary: Unix process tree search
Author: Franck Jouvanceau
Maintainer: Franck Jouvanceau
License-Expression: MIT
Project-URL: Homepage, https://github.com/joknarf/pgtree
Project-URL: Documentation, https://github.com/joknarf/pgtree/blob/master/README.md
Project-URL: Repository, https://github.com/joknarf/pgtree.git
Keywords: shell,pstree,pgrep,process,tree
Classifier: Development Status :: 5 - Production/Stable
Classifier: Intended Audience :: System Administrators
Classifier: Operating System :: POSIX
Classifier: Operating System :: Unix
Classifier: Operating System :: MacOS
Classifier: Programming Language :: Python
Classifier: Programming Language :: Python :: 2
Classifier: Programming Language :: Python :: 2.7
Classifier: Programming Language :: Python :: 3
Classifier: Programming Language :: Python :: 3.6
Classifier: Programming Language :: Python :: 3.7
Classifier: Programming Language :: Python :: 3.8
Classifier: Programming Language :: Python :: 3.9
Classifier: Programming Language :: Python :: 3.10
Classifier: Programming Language :: Python :: 3.11
Classifier: Programming Language :: Python :: 3.12
Classifier: Topic :: Software Development :: Libraries :: Python Modules
Classifier: Topic :: System :: Clustering
Classifier: Topic :: System :: Networking
Classifier: Topic :: System :: Systems Administration
Requires-Python: >=3.6
License-File: LICENSE
Dynamic: license-file
